signicat_api_v2/__init__.py
signicat_api_v2/api.py
signicat_api_v2/request_types.py
signicat_api_v2-1.0.2.dist-info/METADATA
signicat_api_v2-1.0.2.dist-info/WHEEL
signicat_api_v2-1.0.2.dist-info/top_level.txt
signicat_api_v2-1.0.2.dist-info/RECORD
