Metadata-Version: 2.1
Name: signicat-api-v2
Version: 1.0.2
Summary: Rabobank Signicat API wrapper
Author: Theo Bouwman
Author-email: theo.bouwman@swishfund.nl
Maintainer: Ugurcan Akpulat
Maintainer-email: ugurcan.akpulat@swishfund.nl
License: UNKNOWN
Platform: UNKNOWN
Requires-Dist: requests
